.gitignore
LICENSE.rst
README.md
_config.yml
_config.yml.txt
demregpy/__init__.py
demregpy/demmap.py
demregpy/dn2dem.py
demregpy/tresp.py
demregpy/__pycache__/__init__.cpython-38.pyc
demregpy/__pycache__/demmap.cpython-38.pyc
demregpy/__pycache__/dn2dem.cpython-38.pyc
demregpy/examples/testing_new.ipynb
demregpy/tresp/aia_V8_20171210_050627_response_table.txt
demregpy/tresp/aia_tresp_en.dat
demregpy/tresp/aia_tresp_en_nb.dat
demregpy/tresp/aia_trespv9_en.dat
demregpy.egg-info/PKG-INFO
demregpy.egg-info/SOURCES.txt
demregpy.egg-info/dependency_links.txt
demregpy.egg-info/not-zip-safe
demregpy.egg-info/requires.txt
demregpy.egg-info/top_level.txt
demregpy-0.6.2.dist-info/LICENSE.rst
demregpy-0.6.2.dist-info/METADATA
demregpy-0.6.2.dist-info/WHEEL
demregpy-0.6.2.dist-info/top_level.txt
demregpy-0.6.2.dist-info/RECORD
