Metadata-Version: 2.1
Name: demregpy
Version: 0.6.2
Summary: DEM Regularised Inversion Calculation in Python (Hannah & Kontar 2012)
Home-page: https://github.com/alasdairwilson/demregpy
Author: Alasdair Wilson
Author-email: alasdair.wlsn@gmail.com
License: MIT
Platform: UNKNOWN
Requires-Python: >=3.6
Requires-Dist: numpy
Requires-Dist: tqdm
Requires-Dist: threadpoolctl
